_pyhash2.so
pyhash2-0.9.4.dist-info/top_level.txt
pyhash2-0.9.4.dist-info/RECORD
pyhash2-0.9.4.dist-info/LICENSE.txt
pyhash2-0.9.4.dist-info/METADATA
pyhash2-0.9.4.dist-info/WHEEL
pyhash/__init__.py
