Metadata-Version: 2.1
Name: pyhash2
Version: 0.9.4
Summary: A fork of Python Non-cryptographic Hash Library
Home-page: https://github.com/nnnewb/pyfasthash
Download-URL: https://github.com/nnnewb/pyfasthash/releases
Author: weak_ptr
Author-email: weak_ptr@outlook.com
License: Apache Software License
Keywords: hash hashing fasthash
Platform: x86
Platform: x64
Platform: aarch64
Classifier: Development Status :: 5 - Production/Stable
Classifier: Intended Audience :: Developers
Classifier: Intended Audience :: System Administrators
Classifier: License :: OSI Approved :: Apache Software License
Classifier: Natural Language :: English
Classifier: Operating System :: Microsoft :: Windows
Classifier: Operating System :: POSIX
Classifier: Programming Language :: C++
Classifier: Programming Language :: Python
Classifier: Programming Language :: Python :: 2
Classifier: Programming Language :: Python :: 3
Classifier: Programming Language :: Python :: Implementation :: PyPy
Classifier: Topic :: Internet
Classifier: Topic :: Software Development
Classifier: Topic :: Software Development :: Libraries :: Python Modules
Classifier: Topic :: Utilities
License-File: LICENSE.txt
